PiGame/__init__.py
PiGame/helpers.py
PiGame/highscores.txt
PiGame/main.py
PiGame/pi_digits.txt
PiGame/images/heart.png
PiGame/images/logo.png
PiGame/images/minus.png
PiGame/images/plus.png
PiGame/images/switch_neutral.png
PiGame/images/switch_off.png
PiGame/images/switch_on.png
PiMemorizeGame-0.4.dist-info/LICENCE
PiMemorizeGame-0.4.dist-info/METADATA
PiMemorizeGame-0.4.dist-info/WHEEL
PiMemorizeGame-0.4.dist-info/entry_points.txt
PiMemorizeGame-0.4.dist-info/top_level.txt
PiMemorizeGame-0.4.dist-info/RECORD
