Metadata-Version: 2.1
Name: PiMemorizeGame
Version: 0.4
Summary: A game for learning Pi digits through various modes
Home-page: https://github.com/jkarasek/PiGame
License-File: LICENCE
Requires-Dist: pygame-ce>=2.5.2
Requires-Dist: pygame-gui>=0.6.12
Provides-Extra: pygame
